dgl_client/__init__.py
dgl_client/api_cli.py
dgl_client/config.py
dgl_client/main.py
dgl_client/main2.py
dgl_client/utils.py
dgl_client/commands/__init__.py
dgl_client/commands/chat.py
dgl_client/commands/collections.py
dgl_client/commands/login.py
dgl_client/commands/ls.py
dgl_client/commands/utils.py
dgl_client-0.4.11.dist-info/entry_points.txt
dgl_client-0.4.11.dist-info/WHEEL
dgl_client-0.4.11.dist-info/METADATA
dgl_client-0.4.11.dist-info/RECORD
