Metadata-Version: 2.1
Name: dgl_client
Version: 0.4.11
Summary: Command line API client for DigLife
Author-email: Mario Ceresa <mario.ceresa@ec.europa.eu>
Requires-Dist: sseclient-py
Requires-Dist: requests
Requires-Dist: typer
Requires-Dist: rich
Requires-Dist: loguru
Requires-Dist: pydantic-settings
Requires-Dist: pytest ; extra == "dev"
Project-URL: Home, https://github.com/jrcf7/dgl_client
Provides-Extra: dev
